odoo/addons/ai_oca_bridge_document_page/README.rst
odoo/addons/ai_oca_bridge_document_page/__init__.py
odoo/addons/ai_oca_bridge_document_page/__manifest__.py
odoo/addons/ai_oca_bridge_document_page/demo/ai_bridge_demo.xml
odoo/addons/ai_oca_bridge_document_page/i18n/ai_oca_bridge_document_page.pot
odoo/addons/ai_oca_bridge_document_page/i18n/es.po
odoo/addons/ai_oca_bridge_document_page/i18n/es_VE.po
odoo/addons/ai_oca_bridge_document_page/i18n/it.po
odoo/addons/ai_oca_bridge_document_page/i18n/pt_BR.po
odoo/addons/ai_oca_bridge_document_page/models/__init__.py
odoo/addons/ai_oca_bridge_document_page/models/document_page.py
odoo/addons/ai_oca_bridge_document_page/readme/CONFIGURE.md
odoo/addons/ai_oca_bridge_document_page/readme/CONTRIBUTORS.md
odoo/addons/ai_oca_bridge_document_page/readme/DESCRIPTION.md
odoo/addons/ai_oca_bridge_document_page/readme/USAGE.md
odoo/addons/ai_oca_bridge_document_page/static/description/RagCapabilitiesWithOdooKnowledge.json
odoo/addons/ai_oca_bridge_document_page/static/description/icon.png
odoo/addons/ai_oca_bridge_document_page/static/description/index.html
odoo/addons/ai_oca_bridge_document_page/tests/__init__.py
odoo/addons/ai_oca_bridge_document_page/tests/test_document_page_ai_bridge.py
odoo_addon_ai_oca_bridge_document_page-18.0.1.0.0.2.dist-info/METADATA
odoo_addon_ai_oca_bridge_document_page-18.0.1.0.0.2.dist-info/WHEEL
odoo_addon_ai_oca_bridge_document_page-18.0.1.0.0.2.dist-info/top_level.txt
odoo_addon_ai_oca_bridge_document_page-18.0.1.0.0.2.dist-info/RECORD
