Metadata-Version: 2.1
Name: odoo-addon-ai_oca_bridge_document_page
Version: 18.0.1.0.0.2
Requires-Python: >=3.10
Requires-Dist: odoo-addon-ai_oca_bridge==18.0.*
Requires-Dist: odoo-addon-document_page==18.0.*
Requires-Dist: odoo==18.0.*
Summary: Adds Documents synchronization using AI Bridges
Home-page: https://github.com/OCA/ai
License: AGPL-3
Author: Binhex,Odoo Community Association (OCA)
Author-email: support@odoo-community.org
Classifier: Programming Language :: Python
Classifier: Framework :: Odoo
Classifier: Framework :: Odoo :: 18.0
Classifier: License :: OSI Approved :: GNU Affero General Public License v3
